LICENSE
README.md
quest_eras/__init__.py
quest_eras/main.py
quest_eras/es_gui/__init__.py
quest_eras/es_gui/settings.py
quest_eras/es_gui/apps/__init__.py
quest_eras/es_gui/apps/btm/__init__.py
quest_eras/es_gui/apps/btm/cost_savings.py
quest_eras/es_gui/apps/btm/home.py
quest_eras/es_gui/apps/btm/op_handler.py
quest_eras/es_gui/apps/btm/reporting.py
quest_eras/es_gui/apps/btm/results_viewer.py
quest_eras/es_gui/apps/data_manager/__init__.py
quest_eras/es_gui/apps/data_manager/data_manager.py
quest_eras/es_gui/apps/data_manager/home.py
quest_eras/es_gui/apps/data_manager/load.py
quest_eras/es_gui/apps/data_manager/nsrdb.py
quest_eras/es_gui/apps/data_manager/pv.py
quest_eras/es_gui/apps/data_manager/rate_structure.py
quest_eras/es_gui/apps/data_manager/utils.py
quest_eras/es_gui/apps/data_manager/widgets.py
quest_eras/es_gui/apps/performance/__init__.py
quest_eras/es_gui/apps/performance/home.py
quest_eras/es_gui/apps/performance/performance_sim.py
quest_eras/es_gui/apps/performance/performance_sim_handler.py
quest_eras/es_gui/apps/performance/results_viewer.py
quest_eras/es_gui/apps/tech_selection/__init__.py
quest_eras/es_gui/apps/tech_selection/analysis.py
quest_eras/es_gui/apps/tech_selection/fAux.py
quest_eras/es_gui/apps/tech_selection/fFeasibility.py
quest_eras/es_gui/apps/tech_selection/fPlots.py
quest_eras/es_gui/apps/tech_selection/home.py
quest_eras/es_gui/apps/tech_selection/results_viewer.py
quest_eras/es_gui/apps/tech_selection/tech_selection_wizard.py
quest_eras/es_gui/apps/valuation/__init__.py
quest_eras/es_gui/apps/valuation/batchrunscreen.py
quest_eras/es_gui/apps/valuation/home.py
quest_eras/es_gui/apps/valuation/loaddatascreen.py
quest_eras/es_gui/apps/valuation/op_handler.py
quest_eras/es_gui/apps/valuation/reporting.py
quest_eras/es_gui/apps/valuation/results_viewer.py
quest_eras/es_gui/apps/valuation/setparametersscreen.py
quest_eras/es_gui/apps/valuation/valuationscreen.py
quest_eras/es_gui/apps/valuation/wizard.py
quest_eras.egg-info/PKG-INFO
quest_eras.egg-info/SOURCES.txt
quest_eras.egg-info/dependency_links.txt
quest_eras.egg-info/entry_points.txt
quest_eras.egg-info/requires.txt
quest_eras.egg-info/top_level.txt
quest_eras-1.6.6.dist-info/LICENSE
quest_eras-1.6.6.dist-info/METADATA
quest_eras-1.6.6.dist-info/WHEEL
quest_eras-1.6.6.dist-info/entry_points.txt
quest_eras-1.6.6.dist-info/top_level.txt
quest_eras-1.6.6.dist-info/RECORD
